error_web/__init__.py
error_web/codes_http.py
error_web/core.py
error_web/templates/errors/base.html
error_web/templates/errors/default.html
error_web-1.0.2.dist-info/METADATA
error_web-1.0.2.dist-info/WHEEL
error_web-1.0.2.dist-info/top_level.txt
error_web-1.0.2.dist-info/RECORD
