Metadata-Version: 2.4
Name: Error_Web
Version: 1.0.2
Summary: Gestionnaire universel d'erreurs Flask avec descriptions pédagogiques
Requires-Python: >=3.8
Requires-Dist: flask>=2.0
